datasette_llm_usage/__init__.py
datasette_llm_usage-0.1a2.dist-info/licenses/LICENSE
datasette_llm_usage-0.1a2.dist-info/METADATA
datasette_llm_usage-0.1a2.dist-info/WHEEL
datasette_llm_usage-0.1a2.dist-info/entry_points.txt
datasette_llm_usage-0.1a2.dist-info/top_level.txt
datasette_llm_usage-0.1a2.dist-info/RECORD
