Metadata-Version: 2.4
Name: datasette-llm-usage
Version: 0.1a2
Summary: Track usage of LLM tokens in a SQLite table
Author: Simon Willison
License-Expression: Apache-2.0
Project-URL: Homepage, https://github.com/datasette/datasette-llm-usage
Project-URL: Changelog, https://github.com/datasette/datasette-llm-usage/releases
Project-URL: Issues, https://github.com/datasette/datasette-llm-usage/issues
Project-URL: CI, https://github.com/datasette/datasette-llm-usage/actions
Classifier: Framework :: Datasette
Requires-Python: >=3.10
License-File: LICENSE
Requires-Dist: datasette>=1.0a21
Requires-Dist: llm>=0.19
Requires-Dist: sqlite-migrate
Provides-Extra: test
Requires-Dist: pytest; extra == "test"
Requires-Dist: pytest-asyncio; extra == "test"
Dynamic: license-file
